<?xml version="1.0" encoding="windows-1251" standalone="yes"?>
<Object Class="TPDynamicForm" Name="TPCustomActionContentProvider">
  <Left>
    <I>458</I>
  </Left>
  <Top>
    <I>46</I>
  </Top>
  <Width>
    <I>414</I>
  </Width>
  <Height>
    <I>271</I>
  </Height>
  <DesignSize>
    <List>
      <Item Index="0">
        <I>398</I>
      </Item>
      <Item Index="1">
        <I>232</I>
      </Item>
    </List>
  </DesignSize>
  <PixelsPerInch>
    <I>96</I>
  </PixelsPerInch>
  <TextHeight>
    <I>13</I>
  </TextHeight>
  <Object Class="TPContentGroupBox" Name="ContainerForAutoCreatedControls">
    <Left>
      <I>0</I>
    </Left>
    <Top>
      <I>0</I>
    </Top>
    <Width>
      <I>398</I>
    </Width>
    <Height>
      <I>190</I>
    </Height>
    <Anchors>
      <Set>
        <Item>akLeft</Item>
        <Item>akTop</Item>
        <Item>akRight</Item>
        <Item>akBottom</Item>
      </Set>
    </Anchors>
    <TabOrder>
      <I>0</I>
    </TabOrder>
    <ShowContainer>False</ShowContainer>
    <ControlId><![CDATA[{2E813F71-CB5F-4934-93F3-09443C13F61E}]]></ControlId>
    <Object Class="TPContentPageControl">
      <Left>
        <I>0</I>
      </Left>
      <Top>
        <I>0</I>
      </Top>
      <Width>
        <I>398</I>
      </Width>
      <Height>
        <I>190</I>
      </Height>
      <ActivePage>TPContentTabSheet2</ActivePage>
      <Align>alClient</Align>
      <TabOrder>
        <I>0</I>
      </TabOrder>
      <WebColumnSpan>
        <I>0</I>
      </WebColumnSpan>
      <Object Class="TPContentTabSheet" Name="TPContentTabSheet1">
        <Caption><![CDATA[Реквизиты]]></Caption>
        <DesignSize>
          <List>
            <Item Index="0">
              <I>390</I>
            </Item>
            <Item Index="1">
              <I>162</I>
            </Item>
          </List>
        </DesignSize>
        <Object Class="TPContainerGroupBox" Name="TPContainerGroupBox1">
          <Left>
            <I>5</I>
          </Left>
          <Top>
            <I>0</I>
          </Top>
          <Width>
            <I>380</I>
          </Width>
          <Height>
            <I>72</I>
          </Height>
          <Anchors>
            <Set>
              <Item>akLeft</Item>
              <Item>akTop</Item>
              <Item>akRight</Item>
            </Set>
          </Anchors>
          <Caption><![CDATA[Реквизиты]]></Caption>
          <TabOrder>
            <I>0</I>
          </TabOrder>
          <WebColumnSpan>
            <I>0</I>
          </WebColumnSpan>
          <DesignSize>
            <List>
              <Item Index="0">
                <I>380</I>
              </Item>
              <Item Index="1">
                <I>72</I>
              </Item>
            </List>
          </DesignSize>
          <ControlId><![CDATA[{F59FC6F4-ABCE-4A58-893A-599027B2E7C5}]]></ControlId>
          <Object Class="TPContentEdit" Name="SREAL_NAME">
            <Left>
              <I>112</I>
            </Left>
            <Top>
              <I>16</I>
            </Top>
            <Width>
              <I>258</I>
            </Width>
            <WebColumnSpan>
              <I>0</I>
            </WebColumnSpan>
            <Anchors>
              <Set>
                <Item>akTop</Item>
                <Item>akRight</Item>
              </Set>
            </Anchors>
            <ContentDictInterface.Params>
              <Collection/>
            </ContentDictInterface.Params>
            <ControlLabel.Text><![CDATA[Имя файла]]></ControlLabel.Text>
            <MaxLength>
              <I>160</I>
            </MaxLength>
            <Required>True</Required>
            <TabOrder>
              <I>0</I>
            </TabOrder>
            <ReadOnly>True</ReadOnly>
            <ControlId><![CDATA[{4BF7CDA2-5DD8-4431-B4D0-314CF6B50BCB}]]></ControlId>
          </Object>
          <Object Class="TPContentBLOBEdit" Name="BFILEDATA">
            <Left>
              <I>112</I>
            </Left>
            <Top>
              <I>41</I>
            </Top>
            <Width>
              <I>258</I>
            </Width>
            <Height>
              <I>21</I>
            </Height>
            <Anchors>
              <Set>
                <Item>akTop</Item>
                <Item>akRight</Item>
              </Set>
            </Anchors>
            <Caption><![CDATA[BFILEDATA]]></Caption>
            <ControlLabel.Text><![CDATA[Файл]]></ControlLabel.Text>
            <FileNameControl>SREAL_NAME</FileNameControl>
            <Required>True</Required>
            <TabOrder>
              <I>1</I>
            </TabOrder>
            <WebColumnSpan>
              <I>0</I>
            </WebColumnSpan>
            <ControlId><![CDATA[{7611CDB4-C40F-4C76-BE15-29C70074897E}]]></ControlId>
          </Object>
        </Object>
      </Object>
      <Object Class="TPContentTabSheet" Name="TPContentTabSheet2">
        <Caption><![CDATA[Примечание]]></Caption>
        <DesignSize>
          <List>
            <Item Index="0">
              <I>390</I>
            </Item>
            <Item Index="1">
              <I>162</I>
            </Item>
          </List>
        </DesignSize>
        <Object Class="TPContainerGroupBox" Name="TPContainerGroupBox2">
          <Left>
            <I>5</I>
          </Left>
          <Top>
            <I>0</I>
          </Top>
          <Width>
            <I>380</I>
          </Width>
          <Height>
            <I>154</I>
          </Height>
          <Anchors>
            <Set>
              <Item>akLeft</Item>
              <Item>akTop</Item>
              <Item>akRight</Item>
            </Set>
          </Anchors>
          <Caption><![CDATA[Примечание]]></Caption>
          <TabOrder>
            <I>0</I>
          </TabOrder>
          <WebColumnSpan>
            <I>0</I>
          </WebColumnSpan>
          <DesignSize>
            <List>
              <Item Index="0">
                <I>380</I>
              </Item>
              <Item Index="1">
                <I>154</I>
              </Item>
            </List>
          </DesignSize>
          <ControlId><![CDATA[{CC6FC81D-17BF-4B91-9D89-4D0EAE133591}]]></ControlId>
          <Object Class="TPContentMemo" Name="SNOTE">
            <Left>
              <I>10</I>
            </Left>
            <Top>
              <I>17</I>
            </Top>
            <Width>
              <I>360</I>
            </Width>
            <Height>
              <I>127</I>
            </Height>
            <Anchors>
              <Set>
                <Item>akLeft</Item>
                <Item>akTop</Item>
                <Item>akRight</Item>
              </Set>
            </Anchors>
            <ControlLabel.Position>
              <I>0</I>
            </ControlLabel.Position>
            <MaxLength>
              <I>4000</I>
            </MaxLength>
            <TabOrder>
              <I>0</I>
            </TabOrder>
            <WebColumnSpan>
              <I>0</I>
            </WebColumnSpan>
            <WebHeight>
              <I>0</I>
            </WebHeight>
            <ControlId><![CDATA[{EE863044-9FFA-4AC2-BFAC-3769AF0E0CCB}]]></ControlId>
          </Object>
        </Object>
      </Object>
    </Object>
  </Object>
  <Object Class="TPContentCancelButton" Name="CancelButton">
    <Left>
      <I>300</I>
    </Left>
    <Top>
      <I>199</I>
    </Top>
    <Width>
      <I>90</I>
    </Width>
    <Anchors>
      <Set>
        <Item>akRight</Item>
        <Item>akBottom</Item>
      </Set>
    </Anchors>
    <TabOrder>
      <I>2</I>
    </TabOrder>
    <WebColumnSpan>
      <I>0</I>
    </WebColumnSpan>
  </Object>
  <Object Class="TPContentOkButton" Name="OKButton">
    <Left>
      <I>205</I>
    </Left>
    <Top>
      <I>199</I>
    </Top>
    <Width>
      <I>90</I>
    </Width>
    <Anchors>
      <Set>
        <Item>akRight</Item>
        <Item>akBottom</Item>
      </Set>
    </Anchors>
    <TabOrder>
      <I>1</I>
    </TabOrder>
    <WebColumnSpan>
      <I>0</I>
    </WebColumnSpan>
  </Object>
  <Object Class="TPContentUserConditions" Name="AutoCreatedUserConditions">
    <Conditions><![CDATA[<?xml version="1.0" encoding="windows-1251" standalone="yes"?><control-rules/>]]></Conditions>
  </Object>
</Object>
